pidd/__init__.py
pidd/__main__.py
pidd/project.py
pidd/projects.py
pidd-0.0.1.dist-info/METADATA
pidd-0.0.1.dist-info/WHEEL
pidd-0.0.1.dist-info/licenses/license.md
pidd-0.0.1.dist-info/RECORD
